modelos/__init__.py
modelos/config.py
modelos/env/README.md
modelos/env/__init__.py
modelos/env/base.py
modelos/env/image/build.py
modelos/local.py
modelos/log.py
modelos/object/__init__.py
modelos/object/base.py
modelos/object/encoding.py
modelos/object/kind.py
modelos/object/opts.py
modelos/pkg/__init__.py
modelos/pkg/base.py
modelos/pkg/id.py
modelos/pkg/info.py
modelos/pkg/repo/__init__.py
modelos/pkg/repo/base.py
modelos/pkg/repo/gs.py
modelos/pkg/repo/local.py
modelos/pkg/repo/oci.py
modelos/pkg/repo/remote.py
modelos/pkg/repo/s3.py
modelos/pkg/repo/util.py
modelos/pkg/scheme/py.py
modelos/pkg/scheme.py
modelos/pkg/util.py
modelos/pkg/version.py
modelos/run/README.md
modelos/run/client.py
modelos/run/kube/auth_util.py
modelos/run/kube/env.py
modelos/run/kube/pod_util.py
modelos/run/kube/sync.py
modelos/run/kube/uri.py
modelos/scm.py
modelos/util/decorate.py
modelos/util/generic.py
modelos/util/path.py
modelos/util/rootpath.py
modelos/virtual/container/client.py
modelos/virtual/container/file.py
modelos/virtual/container/id.py
modelos/virtual/container/registry.py
modelos-0.1.3.dist-info/LICENSE
modelos-0.1.3.dist-info/WHEEL
modelos-0.1.3.dist-info/METADATA
modelos-0.1.3.dist-info/RECORD
