Metadata-Version: 2.1
Name: modelos
Version: 0.1.3
Summary: An operating system for machine learning
License: Apache 2.0
Author: Patrick Barker
Author-email: patrickbarkerco@gmail.com
Requires-Python: >=3.8,<4.0
Classifier: License :: Other/Proprietary License
Classifier: Programming Language :: Python :: 3
Classifier: Programming Language :: Python :: 3.10
Classifier: Programming Language :: Python :: 3.8
Classifier: Programming Language :: Python :: 3.9
Requires-Dist: GitPython (>=3.1.30,<4.0.0)
Requires-Dist: black (>=23.1.0,<24.0.0)
Requires-Dist: cloudpickle (>=2.2.1,<3.0.0)
Requires-Dist: dataclasses-jsonschema (>=2.16.0,<3.0.0)
Requires-Dist: deepdiff (>=6.2.3,<7.0.0)
Requires-Dist: docker (>=6.0.1,<7.0.0)
Requires-Dist: docker-image-py (>=0.1.12,<0.2.0)
Requires-Dist: isort (>=5.12.0,<6.0.0)
Requires-Dist: kubernetes (>=25.3.0,<26.0.0)
Requires-Dist: lib-programname (>=2.0.5,<3.0.0)
Requires-Dist: ocifacts (>=0.0.9,<0.0.10)
Requires-Dist: opencontainers (>=0.0.14,<0.0.15)
Requires-Dist: removestar (>=1.3.1,<2.0.0)
Requires-Dist: rich (>=13.3.1,<14.0.0)
Requires-Dist: semver (>=2.13.0,<3.0.0)
Requires-Dist: starlette (>=0.24.0,<0.25.0)
Requires-Dist: unimport (>=0.14.1,<0.15.0)
Requires-Dist: uvicorn[standard] (>=0.20.0,<0.21.0)
Requires-Dist: xdg (>=5.1.1,<6.0.0)
